[
    {
        "seed": 3158643,
        "submits": [
            "GoBiggerSubmit.submit.gobigger.level_2.submission_level_2_0",
            "GoBiggerSubmit.submit.gobigger.level_3.submission_level_3_8",
            "GoBiggerSubmit.submit.gobigger.random.submission_random_28",
            "GoBiggerSubmit.submit.gobigger.level_2.submission_level_2_30"
        ],
        "ranks": [
            3,
            0,
            1,
            2
        ],
        "scores": [
            34.959150525392786,
            33424.37148026366,
            6940.275058659165,
            6220.756956564416
        ],
        "time_actions": [
            0.6493666172027588,
            7.362491607666016,
            0.061528921127319336,
            0.44844722747802734
        ],
        "time_cost": 31.21867299079895
    },
    {
        "seed": 35727298,
        "submits": [
            "GoBiggerSubmit.submit.gobigger.level_2.submission_level_2_30",
            "GoBiggerSubmit.submit.gobigger.level_1.submission_level_1_0",
            "GoBiggerSubmit.submit.gobigger.level_1.submission_level_1_10",
            "GoBiggerSubmit.submit.gobigger.level_1.submission_level_1_15"
        ],
        "ranks": [
            3,
            0,
            1,
            2
        ],
        "scores": [
            39.09859000728929,
            43497.05098749565,
            22371.84181361951,
            20436.919155246986
        ],
        "time_actions": [
            0.6541869640350342,
            6.615771055221558,
            4.969515085220337,
            6.027957201004028
        ],
        "time_cost": 27.33971071243286
    },
    {
        "seed": 85886287,
        "submits": [
            "GoBiggerSubmit.submit.gobigger.level_1.submission_level_1_16",
            "GoBiggerSubmit.submit.gobigger.random.submission_random_48",
            "GoBiggerSubmit.submit.gobigger.level_2.submission_level_2_32",
            "GoBiggerSubmit.submit.gobigger.level_3.submission_level_3_38"
        ],
        "ranks": [
            1,
            2,
            3,
            0
        ],
        "scores": [
            22633.92409732678,
            8584.76471713057,
            42.15320050265731,
            40225.83911936305
        ],
        "time_actions": [
            7.3811867237091064,
            0.032837629318237305,
            0.6421301364898682,
            5.801846265792847
        ],
        "time_cost": 26.506916284561157
    },
    {
        "seed": 50413010,
        "submits": [
            "GoBiggerSubmit.submit.gobigger.random.submission_random_18",
            "GoBiggerSubmit.submit.gobigger.level_1.submission_level_1_37",
            "GoBiggerSubmit.submit.gobigger.level_2.submission_level_2_42",
            "GoBiggerSubmit.submit.gobigger.level_3.submission_level_3_1"
        ],
        "ranks": [
            2,
            1,
            3,
            0
        ],
        "scores": [
            3644.4983131356285,
            26192.57878391547,
            27.0,
            37521.671089239084
        ],
        "time_actions": [
            0.035894155502319336,
            7.784853219985962,
            0.4661545753479004,
            8.698323965072632
        ],
        "time_cost": 32.564207792282104
    },
    {
        "seed": 1610986,
        "submits": [
            "GoBiggerSubmit.submit.gobigger.level_3.submission_level_3_14",
            "GoBiggerSubmit.submit.gobigger.random.submission_random_23",
            "GoBiggerSubmit.submit.gobigger.level_1.submission_level_1_15",
            "GoBiggerSubmit.submit.gobigger.random.submission_random_46"
        ],
        "ranks": [
            0,
            3,
            1,
            2
        ],
        "scores": [
            37364.01682789691,
            70.59750327611009,
            28393.10250988791,
            5380.437820979414
        ],
        "time_actions": [
            5.202936887741089,
            0.05041861534118652,
            7.699864387512207,
            0.02368903160095215
        ],
        "time_cost": 28.27095127105713
    },
    {
        "seed": 7620023,
        "submits": [
            "GoBiggerSubmit.submit.gobigger.random.submission_random_42",
            "GoBiggerSubmit.submit.gobigger.level_1.submission_level_1_5",
            "GoBiggerSubmit.submit.gobigger.random.submission_random_48",
            "GoBiggerSubmit.submit.gobigger.level_2.submission_level_2_35"
        ],
        "ranks": [
            1,
            0,
            2,
            3
        ],
        "scores": [
            3061.1461181543564,
            28245.12281114123,
            2561.713286617019,
            122.21393791330907
        ],
        "time_actions": [
            0.049533843994140625,
            7.774791955947876,
            0.0163881778717041,
            0.6712896823883057
        ],
        "time_cost": 26.67835235595703
    },
    {
        "seed": 48057661,
        "submits": [
            "GoBiggerSubmit.submit.gobigger.level_2.submission_level_2_22",
            "GoBiggerSubmit.submit.gobigger.level_2.submission_level_2_27",
            "GoBiggerSubmit.submit.gobigger.level_2.submission_level_2_23",
            "GoBiggerSubmit.submit.gobigger.level_2.submission_level_2_26"
        ],
        "ranks": [
            2,
            1,
            0,
            3
        ],
        "scores": [
            4379.555598600329,
            14342.666365901281,
            68666.46265970358,
            46.882986864780264
        ],
        "time_actions": [
            0.6174430847167969,
            0.8307318687438965,
            1.7006030082702637,
            0.603018045425415
        ],
        "time_cost": 16.97115993499756
    },
    {
        "seed": 24902288,
        "submits": [
            "GoBiggerSubmit.submit.gobigger.level_2.submission_level_2_39",
            "GoBiggerSubmit.submit.gobigger.level_2.submission_level_2_41",
            "GoBiggerSubmit.submit.gobigger.level_1.submission_level_1_33",
            "GoBiggerSubmit.submit.gobigger.random.submission_random_9"
        ],
        "ranks": [
            1,
            3,
            0,
            2
        ],
        "scores": [
            11041.43564929648,
            102.58813996622897,
            19063.272909729476,
            3458.1764555656755
        ],
        "time_actions": [
            0.562098503112793,
            0.507958173751831,
            8.820164442062378,
            0.028421640396118164
        ],
        "time_cost": 30.57463574409485
    },
    {
        "seed": 28624617,
        "submits": [
            "GoBiggerSubmit.submit.gobigger.level_3.submission_level_3_10",
            "GoBiggerSubmit.submit.gobigger.level_2.submission_level_2_29",
            "GoBiggerSubmit.submit.gobigger.level_3.submission_level_3_29",
            "GoBiggerSubmit.submit.gobigger.random.submission_random_25"
        ],
        "ranks": [
            0,
            3,
            1,
            2
        ],
        "scores": [
            40881.63484146769,
            30.688776584014683,
            25738.1626018627,
            6093.139219530987
        ],
        "time_actions": [
            11.137487649917603,
            0.7535037994384766,
            6.545163154602051,
            0.022548198699951172
        ],
        "time_cost": 39.45969820022583
    },
    {
        "seed": 99859515,
        "submits": [
            "GoBiggerSubmit.submit.gobigger.level_3.submission_level_3_31",
            "GoBiggerSubmit.submit.gobigger.level_3.submission_level_3_17",
            "GoBiggerSubmit.submit.gobigger.level_2.submission_level_2_36",
            "GoBiggerSubmit.submit.gobigger.level_3.submission_level_3_28"
        ],
        "ranks": [
            1,
            2,
            3,
            0
        ],
        "scores": [
            24031.721627596435,
            23081.538618662154,
            91.51196728095013,
            33418.08517593165
        ],
        "time_actions": [
            5.679016828536987,
            5.02946925163269,
            0.6742091178894043,
            6.964319944381714
        ],
        "time_cost": 34.749794244766235
    },
    {
        "seed": 91982161,
        "submits": [
            "GoBiggerSubmit.submit.gobigger.random.submission_random_11",
            "GoBiggerSubmit.submit.gobigger.level_3.submission_level_3_6",
            "GoBiggerSubmit.submit.gobigger.level_3.submission_level_3_42",
            "GoBiggerSubmit.submit.gobigger.level_1.submission_level_1_20"
        ],
        "ranks": [
            3,
            0,
            2,
            1
        ],
        "scores": [
            42.828999291468094,
            28368.807753905727,
            25327.14071812958,
            25356.73117480858
        ],
        "time_actions": [
            0.04512739181518555,
            5.674870252609253,
            4.88627290725708,
            5.431854963302612
        ],
        "time_cost": 27.593708753585815
    },
    {
        "seed": 86130949,
        "submits": [
            "GoBiggerSubmit.submit.gobigger.level_2.submission_level_2_46",
            "GoBiggerSubmit.submit.gobigger.level_3.submission_level_3_35",
            "GoBiggerSubmit.submit.gobigger.level_2.submission_level_2_12",
            "GoBiggerSubmit.submit.gobigger.level_2.submission_level_2_22"
        ],
        "ranks": [
            3,
            0,
            1,
            2
        ],
        "scores": [
            70.75083989401003,
            57075.029347859054,
            5456.885249192576,
            961.041479470762
        ],
        "time_actions": [
            0.6125876903533936,
            6.640559673309326,
            1.193199872970581,
            0.6057069301605225
        ],
        "time_cost": 25.7033429145813
    },
    {
        "seed": 35359082,
        "submits": [
            "GoBiggerSubmit.submit.gobigger.level_3.submission_level_3_31",
            "GoBiggerSubmit.submit.gobigger.level_1.submission_level_1_32",
            "GoBiggerSubmit.submit.gobigger.level_2.submission_level_2_14",
            "GoBiggerSubmit.submit.gobigger.random.submission_random_11"
        ],
        "ranks": [
            2,
            1,
            0,
            3
        ],
        "scores": [
            20002.979267194583,
            21892.079190942266,
            23377.700225486584,
            11262.4751489866
        ],
        "time_actions": [
            6.683232069015503,
            8.725435018539429,
            1.112483263015747,
            0.05979633331298828
        ],
        "time_cost": 37.772353410720825
    },
    {
        "seed": 68450623,
        "submits": [
            "GoBiggerSubmit.submit.gobigger.random.submission_random_7",
            "GoBiggerSubmit.submit.gobigger.level_3.submission_level_3_5",
            "GoBiggerSubmit.submit.gobigger.random.submission_random_29",
            "GoBiggerSubmit.submit.gobigger.level_3.submission_level_3_37"
        ],
        "ranks": [
            2,
            1,
            3,
            0
        ],
        "scores": [
            2183.4899153446645,
            24809.071814552008,
            252.33392774157267,
            47961.56810501001
        ],
        "time_actions": [
            0.0601048469543457,
            6.063411474227905,
            0.026190519332885742,
            6.840521574020386
        ],
        "time_cost": 31.62675428390503
    },
    {
        "seed": 67871735,
        "submits": [
            "GoBiggerSubmit.submit.gobigger.level_2.submission_level_2_23",
            "GoBiggerSubmit.submit.gobigger.level_1.submission_level_1_48",
            "GoBiggerSubmit.submit.gobigger.level_2.submission_level_2_8",
            "GoBiggerSubmit.submit.gobigger.level_2.submission_level_2_37"
        ],
        "ranks": [
            2,
            1,
            0,
            3
        ],
        "scores": [
            46.86829202499325,
            25390.913512168838,
            28691.14330136422,
            30.979216111942925
        ],
        "time_actions": [
            0.6712493896484375,
            12.592657089233398,
            1.051567792892456,
            0.5673191547393799
        ],
        "time_cost": 36.10253691673279
    },
    {
        "seed": 79308090,
        "submits": [
            "GoBiggerSubmit.submit.gobigger.random.submission_random_8",
            "GoBiggerSubmit.submit.gobigger.level_1.submission_level_1_24",
            "GoBiggerSubmit.submit.gobigger.random.submission_random_32",
            "GoBiggerSubmit.submit.gobigger.level_3.submission_level_3_25"
        ],
        "ranks": [
            0,
            2,
            3,
            1
        ],
        "scores": [
            24934.870299199218,
            16653.850119530536,
            999.7115504400624,
            23173.331205982988
        ],
        "time_actions": [
            0.0554349422454834,
            5.6830761432647705,
            0.017743587493896484,
            7.401011943817139
        ],
        "time_cost": 29.826241970062256
    },
    {
        "seed": 52741507,
        "submits": [
            "GoBiggerSubmit.submit.gobigger.level_1.submission_level_1_18",
            "GoBiggerSubmit.submit.gobigger.level_1.submission_level_1_26",
            "GoBiggerSubmit.submit.gobigger.level_3.submission_level_3_18",
            "GoBiggerSubmit.submit.gobigger.level_3.submission_level_3_10"
        ],
        "ranks": [
            3,
            2,
            1,
            0
        ],
        "scores": [
            13321.448663629739,
            14577.381293906987,
            19719.784931555027,
            40412.76649272108
        ],
        "time_actions": [
            6.173228979110718,
            4.0179407596588135,
            3.545382261276245,
            4.881717920303345
        ],
        "time_cost": 28.758217096328735
    },
    {
        "seed": 31161708,
        "submits": [
            "GoBiggerSubmit.submit.gobigger.random.submission_random_7",
            "GoBiggerSubmit.submit.cpp.2022_01_09.submission-816672bd",
            "GoBiggerSubmit.submit.gobigger.level_2.submission_level_2_27",
            "GoBiggerSubmit.submit.gobigger.random.submission_random_27"
        ],
        "ranks": [
            2,
            0,
            3,
            1
        ],
        "scores": [
            185.5652154496424,
            67355.94698818395,
            29.812956807797953,
            1350.7826471330025
        ],
        "time_actions": [
            0.05471992492675781,
            12.643104076385498,
            0.7231576442718506,
            0.03107762336730957
        ],
        "time_cost": 26.072253227233887
    },
    {
        "seed": 87184957,
        "submits": [
            "GoBiggerSubmit.submit.gobigger.level_3.submission_level_3_39",
            "GoBiggerSubmit.submit.gobigger.random.submission_random_23",
            "GoBiggerSubmit.submit.gobigger.level_1.submission_level_1_4",
            "GoBiggerSubmit.submit.gobigger.level_3.submission_level_3_22"
        ],
        "ranks": [
            0,
            3,
            2,
            1
        ],
        "scores": [
            38114.10211775742,
            8082.828290927809,
            8957.76202918769,
            20689.792154216317
        ],
        "time_actions": [
            5.753237962722778,
            0.04264044761657715,
            4.497084617614746,
            5.477343320846558
        ],
        "time_cost": 30.5120632648468
    },
    {
        "seed": 74258879,
        "submits": [
            "GoBiggerSubmit.submit.gobigger.level_2.submission_level_2_1",
            "GoBiggerSubmit.submit.gobigger.level_2.submission_level_2_47",
            "GoBiggerSubmit.submit.gobigger.level_3.submission_level_3_8",
            "GoBiggerSubmit.submit.gobigger.level_3.submission_level_3_37"
        ],
        "ranks": [
            3,
            2,
            0,
            1
        ],
        "scores": [
            31.0,
            164.44426654608029,
            44521.41446083362,
            41464.12557008623
        ],
        "time_actions": [
            0.9087972640991211,
            0.5193996429443359,
            5.595548868179321,
            4.520856857299805
        ],
        "time_cost": 25.814114093780518
    }
]