[
    {
        "seed": 30569192,
        "submits": [
            "GoBiggerSubmit.submit.gobigger.level_1.submission_level_1_44",
            "GoBiggerSubmit.submit.gobigger.level_1.submission_level_1_2",
            "GoBiggerSubmit.submit.gobigger.level_2.submission_level_2_3",
            "GoBiggerSubmit.submit.gobigger.random.submission_random_17"
        ],
        "ranks": [
            1,
            0,
            3,
            2
        ],
        "scores": [
            13505.691658113847,
            37932.66471240745,
            292.624753438907,
            5700.457059887431
        ],
        "time_actions": [
            6.458375692367554,
            6.060957431793213,
            0.5310192108154297,
            0.025031328201293945
        ],
        "time_cost": 26.91552186012268
    },
    {
        "seed": 1333508,
        "submits": [
            "GoBiggerSubmit.submit.gobigger.level_1.submission_level_1_28",
            "GoBiggerSubmit.submit.gobigger.level_2.submission_level_2_21",
            "GoBiggerSubmit.submit.gobigger.level_1.submission_level_1_39",
            "GoBiggerSubmit.submit.gobigger.level_2.submission_level_2_3"
        ],
        "ranks": [
            0,
            3,
            1,
            2
        ],
        "scores": [
            32469.361982961138,
            50.85421774850522,
            21746.021052059656,
            20125.446558608237
        ],
        "time_actions": [
            7.870157957077026,
            0.572807788848877,
            4.279796123504639,
            0.7590343952178955
        ],
        "time_cost": 24.25965166091919
    },
    {
        "seed": 34486242,
        "submits": [
            "GoBiggerSubmit.submit.gobigger.level_2.submission_level_2_0",
            "GoBiggerSubmit.submit.gobigger.random.submission_random_22",
            "GoBiggerSubmit.submit.gobigger.random.submission_random_20",
            "GoBiggerSubmit.submit.gobigger.level_3.submission_level_3_1"
        ],
        "ranks": [
            3,
            2,
            1,
            0
        ],
        "scores": [
            147.09208794751862,
            3514.5545374962794,
            4879.432428470978,
            43723.997610984385
        ],
        "time_actions": [
            0.665482759475708,
            0.026821613311767578,
            0.026209354400634766,
            8.568809032440186
        ],
        "time_cost": 29.644967794418335
    },
    {
        "seed": 6362904,
        "submits": [
            "GoBiggerSubmit.submit.gobigger.random.submission_random_33",
            "GoBiggerSubmit.submit.gobigger.level_1.submission_level_1_2",
            "GoBiggerSubmit.submit.gobigger.level_1.submission_level_1_43",
            "GoBiggerSubmit.submit.gobigger.level_1.submission_level_1_36"
        ],
        "ranks": [
            2,
            1,
            3,
            0
        ],
        "scores": [
            13640.595573292247,
            14325.355818593576,
            8015.735443574558,
            25398.86364612527
        ],
        "time_actions": [
            0.04732942581176758,
            6.752779722213745,
            3.926525354385376,
            4.811514139175415
        ],
        "time_cost": 24.36638617515564
    },
    {
        "seed": 83820324,
        "submits": [
            "GoBiggerSubmit.submit.gobigger.level_3.submission_level_3_38",
            "GoBiggerSubmit.submit.gobigger.level_2.submission_level_2_21",
            "GoBiggerSubmit.submit.gobigger.level_3.submission_level_3_29",
            "GoBiggerSubmit.submit.gobigger.random.submission_random_49"
        ],
        "ranks": [
            0,
            3,
            1,
            2
        ],
        "scores": [
            36331.7837953597,
            204.68691541083436,
            23194.349313620136,
            905.1861665680983
        ],
        "time_actions": [
            7.562858819961548,
            0.5875301361083984,
            4.713067293167114,
            0.041316986083984375
        ],
        "time_cost": 33.58487367630005
    },
    {
        "seed": 46995576,
        "submits": [
            "GoBiggerSubmit.submit.gobigger.level_2.submission_level_2_32",
            "GoBiggerSubmit.submit.gobigger.random.submission_random_25",
            "GoBiggerSubmit.submit.gobigger.random.submission_random_21",
            "GoBiggerSubmit.submit.gobigger.level_1.submission_level_1_15"
        ],
        "ranks": [
            3,
            2,
            1,
            0
        ],
        "scores": [
            120.99680131895249,
            2164.656148279437,
            2367.66480508193,
            39605.20700907833
        ],
        "time_actions": [
            0.5614097118377686,
            0.018734455108642578,
            0.026283740997314453,
            11.841206789016724
        ],
        "time_cost": 30.097806453704834
    },
    {
        "seed": 63475083,
        "submits": [
            "GoBiggerSubmit.submit.gobigger.level_2.submission_level_2_31",
            "GoBiggerSubmit.submit.gobigger.level_2.submission_level_2_47",
            "GoBiggerSubmit.submit.gobigger.level_2.submission_level_2_29",
            "GoBiggerSubmit.submit.gobigger.random.submission_random_34"
        ],
        "ranks": [
            3,
            0,
            2,
            1
        ],
        "scores": [
            50.89603045476919,
            9262.811422479444,
            62.63630531066727,
            1851.4108851547514
        ],
        "time_actions": [
            0.6009194850921631,
            0.3139517307281494,
            0.49633193016052246,
            0.03204226493835449
        ],
        "time_cost": 12.99279522895813
    },
    {
        "seed": 57235369,
        "submits": [
            "GoBiggerSubmit.submit.gobigger.random.submission_random_11",
            "GoBiggerSubmit.submit.gobigger.level_2.submission_level_2_11",
            "GoBiggerSubmit.submit.gobigger.level_1.submission_level_1_6",
            "GoBiggerSubmit.submit.gobigger.level_1.submission_level_1_45"
        ],
        "ranks": [
            2,
            3,
            0,
            1
        ],
        "scores": [
            15320.429877642802,
            45.428585276846,
            35817.84095744768,
            16004.848923612213
        ],
        "time_actions": [
            0.029882192611694336,
            0.6512222290039062,
            7.503112316131592,
            7.131471157073975
        ],
        "time_cost": 28.34161877632141
    },
    {
        "seed": 26120557,
        "submits": [
            "GoBiggerSubmit.submit.gobigger.level_1.submission_level_1_3",
            "GoBiggerSubmit.submit.gobigger.random.submission_random_42",
            "GoBiggerSubmit.submit.gobigger.level_1.submission_level_1_43",
            "GoBiggerSubmit.submit.gobigger.level_1.submission_level_1_45"
        ],
        "ranks": [
            2,
            3,
            1,
            0
        ],
        "scores": [
            13373.168437092045,
            196.5203763164305,
            21153.731822753587,
            37061.995331347076
        ],
        "time_actions": [
            3.9269351959228516,
            0.034889936447143555,
            5.59947395324707,
            8.173804998397827
        ],
        "time_cost": 27.193974494934082
    },
    {
        "seed": 66848061,
        "submits": [
            "GoBiggerSubmit.submit.gobigger.level_1.submission_level_1_43",
            "GoBiggerSubmit.submit.gobigger.level_1.submission_level_1_18",
            "GoBiggerSubmit.submit.gobigger.level_3.submission_level_3_34",
            "GoBiggerSubmit.submit.gobigger.level_3.submission_level_3_37"
        ],
        "ranks": [
            1,
            3,
            0,
            2
        ],
        "scores": [
            24992.68296649507,
            4428.138658002139,
            37574.621407385755,
            18319.378858293316
        ],
        "time_actions": [
            6.717270374298096,
            3.9277687072753906,
            5.068518877029419,
            4.004087209701538
        ],
        "time_cost": 28.3729350566864
    },
    {
        "seed": 13341990,
        "submits": [
            "GoBiggerSubmit.submit.gobigger.level_1.submission_level_1_16",
            "GoBiggerSubmit.submit.gobigger.level_1.submission_level_1_11",
            "GoBiggerSubmit.submit.gobigger.level_2.submission_level_2_2",
            "GoBiggerSubmit.submit.gobigger.random.submission_random_9"
        ],
        "ranks": [
            1,
            0,
            3,
            2
        ],
        "scores": [
            17560.649936307367,
            41117.38488786608,
            81.8007854559061,
            10894.373364623149
        ],
        "time_actions": [
            7.057185888290405,
            7.615064382553101,
            0.5510485172271729,
            0.0375676155090332
        ],
        "time_cost": 28.45557188987732
    },
    {
        "seed": 37975408,
        "submits": [
            "GoBiggerSubmit.submit.gobigger.random.submission_random_29",
            "GoBiggerSubmit.submit.gobigger.random.submission_random_47",
            "GoBiggerSubmit.submit.gobigger.random.submission_random_31",
            "GoBiggerSubmit.submit.gobigger.level_3.submission_level_3_41"
        ],
        "ranks": [
            2,
            3,
            1,
            0
        ],
        "scores": [
            2955.8590264591194,
            2919.4147798755394,
            4601.716354959828,
            36819.047888234774
        ],
        "time_actions": [
            0.07023382186889648,
            0.02007150650024414,
            0.017958402633666992,
            10.438794136047363
        ],
        "time_cost": 33.00936722755432
    },
    {
        "seed": 33952590,
        "submits": [
            "GoBiggerSubmit.submit.gobigger.level_2.submission_level_2_44",
            "GoBiggerSubmit.submit.gobigger.random.submission_random_19",
            "GoBiggerSubmit.submit.gobigger.random.submission_random_22",
            "GoBiggerSubmit.submit.gobigger.level_3.submission_level_3_34"
        ],
        "ranks": [
            3,
            2,
            1,
            0
        ],
        "scores": [
            279.5841848496333,
            4336.440699272844,
            5610.417218059771,
            39001.73592375453
        ],
        "time_actions": [
            0.8246853351593018,
            0.028076887130737305,
            0.010576486587524414,
            9.152711153030396
        ],
        "time_cost": 31.982017278671265
    },
    {
        "seed": 28551631,
        "submits": [
            "GoBiggerSubmit.submit.gobigger.random.submission_random_45",
            "GoBiggerSubmit.submit.gobigger.random.submission_random_3",
            "GoBiggerSubmit.submit.gobigger.level_1.submission_level_1_42",
            "GoBiggerSubmit.submit.gobigger.level_2.submission_level_2_15"
        ],
        "ranks": [
            3,
            2,
            0,
            1
        ],
        "scores": [
            233.30565843385148,
            857.9165984895526,
            53169.62542571349,
            2049.5626053271103
        ],
        "time_actions": [
            0.04458165168762207,
            0.027573585510253906,
            11.297154188156128,
            0.6359710693359375
        ],
        "time_cost": 29.336241483688354
    },
    {
        "seed": 13106354,
        "submits": [
            "GoBiggerSubmit.submit.gobigger.level_2.submission_level_2_49",
            "GoBiggerSubmit.submit.gobigger.level_1.submission_level_1_38",
            "GoBiggerSubmit.submit.gobigger.level_1.submission_level_1_2",
            "GoBiggerSubmit.submit.gobigger.level_2.submission_level_2_32"
        ],
        "ranks": [
            0,
            1,
            2,
            3
        ],
        "scores": [
            34157.70588094292,
            32011.806724760005,
            13357.526554071455,
            72.2420474968136
        ],
        "time_actions": [
            0.8844137191772461,
            4.799270153045654,
            5.030080556869507,
            0.4893455505371094
        ],
        "time_cost": 20.335082530975342
    },
    {
        "seed": 71622654,
        "submits": [
            "GoBiggerSubmit.submit.gobigger.random.submission_random_1",
            "GoBiggerSubmit.submit.gobigger.level_2.submission_level_2_46",
            "GoBiggerSubmit.submit.gobigger.random.submission_random_15",
            "GoBiggerSubmit.submit.gobigger.level_2.submission_level_2_18"
        ],
        "ranks": [
            1,
            0,
            2,
            3
        ],
        "scores": [
            3273.3629622483204,
            7440.734916572397,
            1822.6939327329428,
            70.91296836466114
        ],
        "time_actions": [
            0.03689432144165039,
            0.5684857368469238,
            0.019240140914916992,
            0.4307265281677246
        ],
        "time_cost": 14.883111000061035
    },
    {
        "seed": 40645637,
        "submits": [
            "GoBiggerSubmit.submit.gobigger.random.submission_random_32",
            "GoBiggerSubmit.submit.gobigger.level_2.submission_level_2_24",
            "GoBiggerSubmit.submit.gobigger.level_1.submission_level_1_33",
            "GoBiggerSubmit.submit.gobigger.random.submission_random_26"
        ],
        "ranks": [
            1,
            3,
            0,
            2
        ],
        "scores": [
            4577.469385672375,
            64.6901567818162,
            27856.256954094384,
            4266.231612687937
        ],
        "time_actions": [
            0.03140091896057129,
            0.619680643081665,
            9.98323130607605,
            0.020702362060546875
        ],
        "time_cost": 28.32087731361389
    },
    {
        "seed": 23099433,
        "submits": [
            "GoBiggerSubmit.submit.gobigger.level_1.submission_level_1_2",
            "GoBiggerSubmit.submit.gobigger.level_2.submission_level_2_1",
            "GoBiggerSubmit.submit.gobigger.level_2.submission_level_2_31",
            "GoBiggerSubmit.submit.gobigger.random.submission_random_7"
        ],
        "ranks": [
            2,
            3,
            1,
            0
        ],
        "scores": [
            10305.95333456842,
            231.51693043379262,
            12791.17456124327,
            39679.259912166104
        ],
        "time_actions": [
            6.822993040084839,
            0.5084149837493896,
            1.1121456623077393,
            0.02445530891418457
        ],
        "time_cost": 19.768629550933838
    },
    {
        "seed": 59127530,
        "submits": [
            "GoBiggerSubmit.submit.gobigger.level_3.submission_level_3_5",
            "GoBiggerSubmit.submit.gobigger.level_3.submission_level_3_18",
            "GoBiggerSubmit.submit.gobigger.level_2.submission_level_2_0",
            "GoBiggerSubmit.submit.gobigger.level_2.submission_level_2_48"
        ],
        "ranks": [
            1,
            0,
            3,
            2
        ],
        "scores": [
            29881.79393020617,
            31719.346480915723,
            70.82941116650096,
            7126.31617804755
        ],
        "time_actions": [
            5.114344120025635,
            5.673758268356323,
            0.4642491340637207,
            0.5108766555786133
        ],
        "time_cost": 24.875558614730835
    },
    {
        "seed": 57358862,
        "submits": [
            "GoBiggerSubmit.submit.gobigger.random.submission_random_37",
            "GoBiggerSubmit.submit.gobigger.level_2.submission_level_2_30",
            "GoBiggerSubmit.submit.gobigger.level_3.submission_level_3_31",
            "GoBiggerSubmit.submit.gobigger.level_1.submission_level_1_27"
        ],
        "ranks": [
            2,
            3,
            0,
            1
        ],
        "scores": [
            12237.796602901612,
            125.53262863107261,
            33459.41065898606,
            16133.054957069016
        ],
        "time_actions": [
            0.044274091720581055,
            0.5536062717437744,
            4.997135877609253,
            4.095118761062622
        ],
        "time_cost": 20.065600633621216
    }
]