[
    {
        "seed": 8329151,
        "submits": [
            "GoBiggerSubmit.submit.gobigger.random.submission_random_35",
            "GoBiggerSubmit.submit.gobigger.random.submission_random_16",
            "GoBiggerSubmit.submit.gobigger.level_3.submission_level_3_27",
            "GoBiggerSubmit.submit.gobigger.level_2.submission_level_2_34"
        ],
        "ranks": [
            2,
            1,
            0,
            3
        ],
        "scores": [
            1591.1207246112313,
            3499.6616250441953,
            38691.05410605851,
            216.38090209678185
        ],
        "time_actions": [
            0.07166481018066406,
            0.013631582260131836,
            10.963267803192139,
            0.7826635837554932
        ],
        "time_cost": 45.77375102043152
    },
    {
        "seed": 33601543,
        "submits": [
            "GoBiggerSubmit.submit.gobigger.level_3.submission_level_3_48",
            "GoBiggerSubmit.submit.gobigger.level_3.submission_level_3_45",
            "GoBiggerSubmit.submit.gobigger.level_1.submission_level_1_30",
            "GoBiggerSubmit.submit.cpp.2022_01_09.submission-816672bd"
        ],
        "ranks": [
            2,
            0,
            3,
            1
        ],
        "scores": [
            20440.432814163953,
            36021.61260400465,
            8902.12441060846,
            20667.990875980136
        ],
        "time_actions": [
            4.389068603515625,
            6.492547273635864,
            4.853662967681885,
            3.3205456733703613
        ],
        "time_cost": 30.312464475631714
    },
    {
        "seed": 59677848,
        "submits": [
            "GoBiggerSubmit.submit.gobigger.level_2.submission_level_2_38",
            "GoBiggerSubmit.submit.gobigger.random.submission_random_11",
            "GoBiggerSubmit.submit.gobigger.level_2.submission_level_2_41",
            "GoBiggerSubmit.submit.gobigger.random.submission_random_40"
        ],
        "ranks": [
            3,
            2,
            0,
            1
        ],
        "scores": [
            114.67124498319194,
            1850.5121076476707,
            5794.121260458069,
            2120.836181487966
        ],
        "time_actions": [
            0.6161296367645264,
            0.04428458213806152,
            0.48411130905151367,
            0.02594923973083496
        ],
        "time_cost": 16.567312479019165
    },
    {
        "seed": 54047368,
        "submits": [
            "GoBiggerSubmit.submit.gobigger.level_3.submission_level_3_1",
            "GoBiggerSubmit.submit.gobigger.random.submission_random_19",
            "GoBiggerSubmit.submit.gobigger.none.submission_none_1",
            "GoBiggerSubmit.submit.gobigger.level_1.submission_level_1_43"
        ],
        "ranks": [
            0,
            2,
            3,
            1
        ],
        "scores": [
            30552.223195891955,
            4602.731990697936,
            27.0,
            24613.86775964269
        ],
        "time_actions": [
            7.415206432342529,
            0.06422138214111328,
            0.01537775993347168,
            7.982767820358276
        ],
        "time_cost": 34.6315758228302
    },
    {
        "seed": 95253283,
        "submits": [
            "GoBiggerSubmit.submit.gobigger.random.submission_random_2",
            "GoBiggerSubmit.submit.gobigger.level_2.submission_level_2_12",
            "GoBiggerSubmit.submit.gobigger.level_2.submission_level_2_34",
            "GoBiggerSubmit.submit.gobigger.level_2.submission_level_2_21"
        ],
        "ranks": [
            1,
            0,
            3,
            2
        ],
        "scores": [
            2199.060264107758,
            9523.48675725134,
            90.73762478160904,
            126.70560732689171
        ],
        "time_actions": [
            0.059870004653930664,
            0.4388909339904785,
            0.5977840423583984,
            0.5176301002502441
        ],
        "time_cost": 15.788578510284424
    },
    {
        "seed": 86615866,
        "submits": [
            "GoBiggerSubmit.submit.gobigger.level_1.submission_level_1_2",
            "GoBiggerSubmit.submit.gobigger.random.submission_random_18",
            "GoBiggerSubmit.submit.gobigger.level_1.submission_level_1_18",
            "GoBiggerSubmit.submit.gobigger.level_1.submission_level_1_32"
        ],
        "ranks": [
            2,
            3,
            1,
            0
        ],
        "scores": [
            4655.78236108023,
            2457.8430321004803,
            6954.807447023757,
            42730.2963778236
        ],
        "time_actions": [
            4.616239786148071,
            0.04759097099304199,
            5.154242753982544,
            7.684490919113159
        ],
        "time_cost": 29.741924047470093
    },
    {
        "seed": 83947864,
        "submits": [
            "GoBiggerSubmit.submit.gobigger.level_3.submission_level_3_19",
            "GoBiggerSubmit.submit.gobigger.level_3.submission_level_3_18",
            "GoBiggerSubmit.submit.gobigger.level_1.submission_level_1_5",
            "GoBiggerSubmit.submit.gobigger.level_3.submission_level_3_8"
        ],
        "ranks": [
            2,
            1,
            3,
            0
        ],
        "scores": [
            16335.050861368958,
            30770.858883377095,
            4405.232275708482,
            38076.34021415989
        ],
        "time_actions": [
            4.545316934585571,
            6.421354293823242,
            4.265666723251343,
            4.883956670761108
        ],
        "time_cost": 32.05169677734375
    },
    {
        "seed": 67236634,
        "submits": [
            "GoBiggerSubmit.submit.gobigger.level_1.submission_level_1_43",
            "GoBiggerSubmit.submit.gobigger.random.submission_random_10",
            "GoBiggerSubmit.submit.gobigger.level_2.submission_level_2_38",
            "GoBiggerSubmit.submit.gobigger.level_3.submission_level_3_4"
        ],
        "ranks": [
            1,
            2,
            3,
            0
        ],
        "scores": [
            13970.519482434562,
            1743.5882497975867,
            73.39405354334025,
            52824.6299921671
        ],
        "time_actions": [
            5.496220827102661,
            0.038280487060546875,
            0.7640118598937988,
            6.179320812225342
        ],
        "time_cost": 28.471275806427002
    },
    {
        "seed": 44424276,
        "submits": [
            "GoBiggerSubmit.submit.gobigger.level_1.submission_level_1_38",
            "GoBiggerSubmit.submit.gobigger.random.submission_random_27",
            "GoBiggerSubmit.submit.gobigger.random.submission_random_31",
            "GoBiggerSubmit.submit.gobigger.level_3.submission_level_3_28"
        ],
        "ranks": [
            1,
            3,
            2,
            0
        ],
        "scores": [
            15701.269918464011,
            2511.5435535600936,
            8826.591655247743,
            35215.87857076484
        ],
        "time_actions": [
            7.047757148742676,
            0.06499934196472168,
            0.029008865356445312,
            8.95745038986206
        ],
        "time_cost": 35.91876244544983
    },
    {
        "seed": 41978234,
        "submits": [
            "GoBiggerSubmit.submit.gobigger.random.submission_random_24",
            "GoBiggerSubmit.submit.gobigger.level_1.submission_level_1_44",
            "GoBiggerSubmit.submit.gobigger.random.submission_random_21",
            "GoBiggerSubmit.submit.gobigger.level_3.submission_level_3_24"
        ],
        "ranks": [
            2,
            0,
            3,
            1
        ],
        "scores": [
            3228.810751042938,
            48763.45404006217,
            78.28181106868938,
            19979.169017584838
        ],
        "time_actions": [
            0.05193972587585449,
            8.420439958572388,
            0.03482675552368164,
            4.067476987838745
        ],
        "time_cost": 28.44774889945984
    },
    {
        "seed": 93311695,
        "submits": [
            "GoBiggerSubmit.submit.gobigger.level_1.submission_level_1_12",
            "GoBiggerSubmit.submit.gobigger.level_3.submission_level_3_31",
            "GoBiggerSubmit.submit.gobigger.random.submission_random_41",
            "GoBiggerSubmit.submit.gobigger.level_3.submission_level_3_25"
        ],
        "ranks": [
            2,
            1,
            3,
            0
        ],
        "scores": [
            8097.489404531788,
            22699.94450843876,
            206.48987904709244,
            48449.859602117176
        ],
        "time_actions": [
            5.821447849273682,
            4.753140926361084,
            0.04634833335876465,
            6.913400888442993
        ],
        "time_cost": 31.096883296966553
    },
    {
        "seed": 38144867,
        "submits": [
            "GoBiggerSubmit.submit.gobigger.level_1.submission_level_1_0",
            "GoBiggerSubmit.submit.gobigger.level_1.submission_level_1_44",
            "GoBiggerSubmit.submit.gobigger.random.submission_random_39",
            "GoBiggerSubmit.submit.gobigger.level_1.submission_level_1_23"
        ],
        "ranks": [
            0,
            1,
            2,
            3
        ],
        "scores": [
            31628.019511869414,
            15611.487472060599,
            12540.366255347948,
            8781.918927216178
        ],
        "time_actions": [
            7.143536329269409,
            4.319889307022095,
            0.06359267234802246,
            5.554542064666748
        ],
        "time_cost": 27.48400592803955
    },
    {
        "seed": 62888064,
        "submits": [
            "GoBiggerSubmit.submit.gobigger.level_2.submission_level_2_39",
            "GoBiggerSubmit.submit.gobigger.random.submission_random_9",
            "GoBiggerSubmit.submit.gobigger.level_1.submission_level_1_23",
            "GoBiggerSubmit.submit.gobigger.level_2.submission_level_2_31"
        ],
        "ranks": [
            3,
            1,
            2,
            0
        ],
        "scores": [
            3946.071969631271,
            6960.544393303502,
            5839.9038184463125,
            50449.0448153901
        ],
        "time_actions": [
            0.6547501087188721,
            0.04638481140136719,
            4.769627571105957,
            1.3496246337890625
        ],
        "time_cost": 23.336464166641235
    },
    {
        "seed": 57234546,
        "submits": [
            "GoBiggerSubmit.submit.gobigger.level_2.submission_level_2_48",
            "GoBiggerSubmit.submit.gobigger.level_1.submission_level_1_3",
            "GoBiggerSubmit.submit.gobigger.level_2.submission_level_2_30",
            "GoBiggerSubmit.submit.gobigger.level_1.submission_level_1_45"
        ],
        "ranks": [
            3,
            0,
            2,
            1
        ],
        "scores": [
            34.35630207599415,
            44442.875956484364,
            4235.688633388909,
            27494.95355092035
        ],
        "time_actions": [
            0.5857219696044922,
            9.603356122970581,
            0.5588843822479248,
            10.04323410987854
        ],
        "time_cost": 34.062050580978394
    },
    {
        "seed": 12849161,
        "submits": [
            "GoBiggerSubmit.submit.gobigger.level_1.submission_level_1_6",
            "GoBiggerSubmit.submit.gobigger.level_2.submission_level_2_3",
            "GoBiggerSubmit.submit.gobigger.level_1.submission_level_1_31",
            "GoBiggerSubmit.submit.gobigger.random.submission_random_8"
        ],
        "ranks": [
            1,
            3,
            0,
            2
        ],
        "scores": [
            22283.24070236095,
            27.0,
            42336.08002693555,
            140.97977226797627
        ],
        "time_actions": [
            6.537317991256714,
            0.5977213382720947,
            8.117134809494019,
            0.06535887718200684
        ],
        "time_cost": 33.229902267456055
    },
    {
        "seed": 21274136,
        "submits": [
            "GoBiggerSubmit.submit.gobigger.level_2.submission_level_2_5",
            "GoBiggerSubmit.submit.gobigger.random.submission_random_26",
            "GoBiggerSubmit.submit.gobigger.level_1.submission_level_1_44",
            "GoBiggerSubmit.submit.gobigger.level_3.submission_level_3_42"
        ],
        "ranks": [
            3,
            2,
            1,
            0
        ],
        "scores": [
            1790.4382965487519,
            2761.7849933040598,
            29268.419713025978,
            32575.565351027624
        ],
        "time_actions": [
            0.8735086917877197,
            0.0506744384765625,
            10.677589893341064,
            10.070982694625854
        ],
        "time_cost": 45.32003355026245
    },
    {
        "seed": 17493485,
        "submits": [
            "GoBiggerSubmit.submit.gobigger.random.submission_random_26",
            "GoBiggerSubmit.submit.cpp.2022_01_09.submission-5b0e3de2",
            "GoBiggerSubmit.submit.gobigger.level_3.submission_level_3_17",
            "GoBiggerSubmit.submit.gobigger.level_1.submission_level_1_42"
        ],
        "ranks": [
            2,
            1,
            0,
            3
        ],
        "scores": [
            18417.380078914088,
            23944.543128576523,
            29660.108700447105,
            10679.210395799531
        ],
        "time_actions": [
            0.0645439624786377,
            4.648681402206421,
            5.466731071472168,
            4.448112964630127
        ],
        "time_cost": 24.23259735107422
    },
    {
        "seed": 15114561,
        "submits": [
            "GoBiggerSubmit.submit.gobigger.none.submission_none_0",
            "GoBiggerSubmit.submit.gobigger.level_2.submission_level_2_20",
            "GoBiggerSubmit.submit.gobigger.level_1.submission_level_1_6",
            "GoBiggerSubmit.submit.gobigger.level_3.submission_level_3_35"
        ],
        "ranks": [
            3,
            2,
            1,
            0
        ],
        "scores": [
            27.0,
            6594.760909196351,
            16543.528963098324,
            33785.40327364216
        ],
        "time_actions": [
            0.024409770965576172,
            0.5626475811004639,
            4.75817084312439,
            6.7338244915008545
        ],
        "time_cost": 29.91077971458435
    },
    {
        "seed": 79917184,
        "submits": [
            "GoBiggerSubmit.submit.gobigger.level_3.submission_level_3_43",
            "GoBiggerSubmit.submit.gobigger.level_1.submission_level_1_34",
            "GoBiggerSubmit.submit.gobigger.random.submission_random_27",
            "GoBiggerSubmit.submit.gobigger.level_2.submission_level_2_46"
        ],
        "ranks": [
            0,
            1,
            2,
            3
        ],
        "scores": [
            43095.17867272707,
            8225.55437029519,
            6371.66851857577,
            136.14623103143848
        ],
        "time_actions": [
            5.596804857254028,
            4.04018235206604,
            0.04928183555603027,
            0.5566442012786865
        ],
        "time_cost": 25.205608129501343
    },
    {
        "seed": 62616139,
        "submits": [
            "GoBiggerSubmit.submit.gobigger.random.submission_random_5",
            "GoBiggerSubmit.submit.gobigger.level_3.submission_level_3_27",
            "GoBiggerSubmit.submit.gobigger.random.submission_random_21",
            "GoBiggerSubmit.submit.gobigger.level_2.submission_level_2_4"
        ],
        "ranks": [
            2,
            0,
            1,
            3
        ],
        "scores": [
            710.1580180555525,
            47258.892596898775,
            3311.972283236154,
            84.87546528212184
        ],
        "time_actions": [
            0.042839765548706055,
            7.677329063415527,
            0.02662348747253418,
            0.46926116943359375
        ],
        "time_cost": 28.577117204666138
    }
]