[
    {
        "seed": 63848424,
        "submits": [
            "GoBiggerSubmit.submit.gobigger.level_3.submission_level_3_26",
            "GoBiggerSubmit.submit.gobigger.random.submission_random_9",
            "GoBiggerSubmit.submit.gobigger.level_3.submission_level_3_9",
            "GoBiggerSubmit.submit.gobigger.level_1.submission_level_1_24"
        ],
        "ranks": [
            0,
            3,
            2,
            1
        ],
        "scores": [
            35724.12437526235,
            4385.110563718172,
            17800.754998033863,
            19958.738025561488
        ],
        "time_actions": [
            7.136942148208618,
            0.035542964935302734,
            5.170848369598389,
            5.686841249465942
        ],
        "time_cost": 30.428725004196167
    },
    {
        "seed": 89136982,
        "submits": [
            "GoBiggerSubmit.submit.gobigger.level_2.submission_level_2_28",
            "GoBiggerSubmit.submit.gobigger.level_3.submission_level_3_24",
            "GoBiggerSubmit.submit.gobigger.random.submission_random_21",
            "GoBiggerSubmit.submit.gobigger.level_2.submission_level_2_1"
        ],
        "ranks": [
            3,
            0,
            1,
            2
        ],
        "scores": [
            213.28033210246252,
            39076.99837687939,
            4375.241708754395,
            659.9517007301881
        ],
        "time_actions": [
            0.687152624130249,
            10.846649885177612,
            0.05901145935058594,
            0.5009422302246094
        ],
        "time_cost": 36.62920355796814
    },
    {
        "seed": 8088860,
        "submits": [
            "GoBiggerSubmit.submit.gobigger.none.submission_none_1",
            "GoBiggerSubmit.submit.gobigger.level_1.submission_level_1_43",
            "GoBiggerSubmit.submit.gobigger.random.submission_random_12",
            "GoBiggerSubmit.submit.gobigger.level_1.submission_level_1_2"
        ],
        "ranks": [
            3,
            0,
            2,
            1
        ],
        "scores": [
            27.0,
            44387.25324548974,
            214.71716028356838,
            25463.590771396397
        ],
        "time_actions": [
            0.018314838409423828,
            6.43512225151062,
            0.03936004638671875,
            6.604477167129517
        ],
        "time_cost": 24.483492136001587
    },
    {
        "seed": 49198969,
        "submits": [
            "GoBiggerSubmit.submit.gobigger.level_3.submission_level_3_14",
            "GoBiggerSubmit.submit.gobigger.level_3.submission_level_3_29",
            "GoBiggerSubmit.submit.gobigger.level_3.submission_level_3_41",
            "GoBiggerSubmit.submit.gobigger.level_3.submission_level_3_20"
        ],
        "ranks": [
            3,
            0,
            2,
            1
        ],
        "scores": [
            17426.906653752358,
            28087.15341785654,
            22681.40707047538,
            22685.429380460704
        ],
        "time_actions": [
            5.135732173919678,
            5.144040107727051,
            4.079150915145874,
            4.1634063720703125
        ],
        "time_cost": 33.12608194351196
    },
    {
        "seed": 70993195,
        "submits": [
            "GoBiggerSubmit.submit.gobigger.level_2.submission_level_2_5",
            "GoBiggerSubmit.submit.gobigger.level_3.submission_level_3_16",
            "GoBiggerSubmit.submit.gobigger.random.submission_random_10",
            "GoBiggerSubmit.submit.gobigger.none.submission_none_1"
        ],
        "ranks": [
            1,
            0,
            2,
            3
        ],
        "scores": [
            6191.706593450344,
            37345.58351666719,
            5653.476948433781,
            34.37838393638347
        ],
        "time_actions": [
            0.614891767501831,
            12.13690996170044,
            0.08817505836486816,
            0.0052454471588134766
        ],
        "time_cost": 40.55853033065796
    },
    {
        "seed": 32943182,
        "submits": [
            "GoBiggerSubmit.submit.gobigger.level_1.submission_level_1_21",
            "GoBiggerSubmit.submit.gobigger.level_1.submission_level_1_11",
            "GoBiggerSubmit.submit.gobigger.level_3.submission_level_3_13",
            "GoBiggerSubmit.submit.cpp.2022_01_09.submission-816672bd"
        ],
        "ranks": [
            2,
            1,
            0,
            3
        ],
        "scores": [
            12053.201919590385,
            23690.134663009667,
            45820.48425769853,
            7916.389640653247
        ],
        "time_actions": [
            3.7027902603149414,
            4.62715220451355,
            4.690344572067261,
            2.338860034942627
        ],
        "time_cost": 22.957340478897095
    },
    {
        "seed": 63554522,
        "submits": [
            "GoBiggerSubmit.submit.gobigger.level_2.submission_level_2_43",
            "GoBiggerSubmit.submit.gobigger.random.submission_random_33",
            "GoBiggerSubmit.submit.gobigger.level_3.submission_level_3_0",
            "GoBiggerSubmit.submit.gobigger.random.submission_random_5"
        ],
        "ranks": [
            3,
            1,
            0,
            2
        ],
        "scores": [
            815.0762115910844,
            5884.027457380439,
            40730.936156615855,
            1069.2435893130146
        ],
        "time_actions": [
            0.6027898788452148,
            0.04275345802307129,
            11.898626565933228,
            0.032195091247558594
        ],
        "time_cost": 39.47370100021362
    },
    {
        "seed": 78063847,
        "submits": [
            "GoBiggerSubmit.submit.gobigger.level_3.submission_level_3_34",
            "GoBiggerSubmit.submit.gobigger.level_1.submission_level_1_49",
            "GoBiggerSubmit.submit.gobigger.level_1.submission_level_1_10",
            "GoBiggerSubmit.submit.gobigger.level_1.submission_level_1_40"
        ],
        "ranks": [
            0,
            3,
            2,
            1
        ],
        "scores": [
            54587.058871688096,
            10611.174190384538,
            19809.339062628198,
            23057.802087309436
        ],
        "time_actions": [
            5.878466606140137,
            4.1194679737091064,
            6.3906049728393555,
            5.772213935852051
        ],
        "time_cost": 31.020670652389526
    },
    {
        "seed": 3651642,
        "submits": [
            "GoBiggerSubmit.submit.gobigger.random.submission_random_14",
            "GoBiggerSubmit.submit.gobigger.level_1.submission_level_1_48",
            "GoBiggerSubmit.submit.gobigger.level_3.submission_level_3_46",
            "GoBiggerSubmit.submit.gobigger.level_3.submission_level_3_11"
        ],
        "ranks": [
            3,
            2,
            1,
            0
        ],
        "scores": [
            1219.2046758485067,
            11214.470106359293,
            28179.60463964994,
            34376.11566149294
        ],
        "time_actions": [
            0.050261735916137695,
            4.332215309143066,
            5.093854904174805,
            6.055572986602783
        ],
        "time_cost": 29.473881244659424
    },
    {
        "seed": 35893870,
        "submits": [
            "GoBiggerSubmit.submit.gobigger.level_1.submission_level_1_38",
            "GoBiggerSubmit.submit.gobigger.level_1.submission_level_1_18",
            "GoBiggerSubmit.submit.gobigger.level_3.submission_level_3_17",
            "GoBiggerSubmit.submit.gobigger.level_2.submission_level_2_7"
        ],
        "ranks": [
            1,
            2,
            0,
            3
        ],
        "scores": [
            24184.216274508075,
            16149.298699736235,
            40885.65281239939,
            57.06227471758449
        ],
        "time_actions": [
            5.8027589321136475,
            4.952918529510498,
            6.5869810581207275,
            0.615013837814331
        ],
        "time_cost": 28.360395431518555
    },
    {
        "seed": 80815125,
        "submits": [
            "GoBiggerSubmit.submit.gobigger.level_1.submission_level_1_18",
            "GoBiggerSubmit.submit.gobigger.level_3.submission_level_3_6",
            "GoBiggerSubmit.submit.gobigger.level_1.submission_level_1_2",
            "GoBiggerSubmit.submit.gobigger.level_3.submission_level_3_24"
        ],
        "ranks": [
            2,
            0,
            3,
            1
        ],
        "scores": [
            14603.538838301929,
            34094.24223378055,
            7902.9271166036,
            29531.008947869002
        ],
        "time_actions": [
            5.045610189437866,
            4.792837381362915,
            3.867042064666748,
            4.223530292510986
        ],
        "time_cost": 28.172462940216064
    },
    {
        "seed": 14533326,
        "submits": [
            "GoBiggerSubmit.submit.gobigger.level_2.submission_level_2_42",
            "GoBiggerSubmit.submit.gobigger.level_2.submission_level_2_39",
            "GoBiggerSubmit.submit.gobigger.level_2.submission_level_2_34",
            "GoBiggerSubmit.submit.gobigger.random.submission_random_26"
        ],
        "ranks": [
            3,
            0,
            2,
            1
        ],
        "scores": [
            94.68269561874618,
            10228.689679020099,
            217.41318540047217,
            3460.442849323622
        ],
        "time_actions": [
            0.5091969966888428,
            0.4624063968658447,
            0.43801140785217285,
            0.04800248146057129
        ],
        "time_cost": 14.986334800720215
    },
    {
        "seed": 50661630,
        "submits": [
            "GoBiggerSubmit.submit.gobigger.level_1.submission_level_1_0",
            "GoBiggerSubmit.submit.gobigger.level_2.submission_level_2_17",
            "GoBiggerSubmit.submit.gobigger.level_1.submission_level_1_17",
            "GoBiggerSubmit.submit.gobigger.level_2.submission_level_2_26"
        ],
        "ranks": [
            1,
            3,
            0,
            2
        ],
        "scores": [
            19780.461258509244,
            2085.9076586850074,
            44167.4381895301,
            2145.9158265808755
        ],
        "time_actions": [
            6.392965793609619,
            0.632988452911377,
            7.933146715164185,
            0.7677373886108398
        ],
        "time_cost": 27.065380573272705
    },
    {
        "seed": 21727077,
        "submits": [
            "GoBiggerSubmit.submit.gobigger.level_1.submission_level_1_43",
            "GoBiggerSubmit.submit.gobigger.level_2.submission_level_2_22",
            "GoBiggerSubmit.submit.gobigger.level_1.submission_level_1_44",
            "GoBiggerSubmit.submit.gobigger.level_1.submission_level_1_26"
        ],
        "ranks": [
            0,
            3,
            2,
            1
        ],
        "scores": [
            24733.346647247872,
            75.93288577616684,
            20096.179822576632,
            21671.635819782656
        ],
        "time_actions": [
            3.8138859272003174,
            0.5301191806793213,
            5.241123676300049,
            6.120134592056274
        ],
        "time_cost": 24.408074378967285
    },
    {
        "seed": 51407083,
        "submits": [
            "GoBiggerSubmit.submit.gobigger.level_3.submission_level_3_26",
            "GoBiggerSubmit.submit.gobigger.level_2.submission_level_2_33",
            "GoBiggerSubmit.submit.gobigger.random.submission_random_23",
            "GoBiggerSubmit.submit.gobigger.level_1.submission_level_1_36"
        ],
        "ranks": [
            0,
            3,
            2,
            1
        ],
        "scores": [
            41806.80411138669,
            81.64046046115112,
            8353.160744963932,
            11720.981705825532
        ],
        "time_actions": [
            9.324486494064331,
            0.617703914642334,
            0.04259347915649414,
            4.218806266784668
        ],
        "time_cost": 34.37720203399658
    },
    {
        "seed": 37240647,
        "submits": [
            "GoBiggerSubmit.submit.gobigger.random.submission_random_27",
            "GoBiggerSubmit.submit.gobigger.level_2.submission_level_2_19",
            "GoBiggerSubmit.submit.gobigger.level_1.submission_level_1_3",
            "GoBiggerSubmit.submit.gobigger.level_3.submission_level_3_37"
        ],
        "ranks": [
            2,
            3,
            1,
            0
        ],
        "scores": [
            2873.067406025851,
            1589.2330719789077,
            14409.901921837067,
            40402.613584151186
        ],
        "time_actions": [
            0.04478740692138672,
            0.6499619483947754,
            5.191303730010986,
            9.822916984558105
        ],
        "time_cost": 36.30120635032654
    },
    {
        "seed": 35174900,
        "submits": [
            "GoBiggerSubmit.submit.gobigger.level_3.submission_level_3_26",
            "GoBiggerSubmit.submit.gobigger.none.submission_none_0",
            "GoBiggerSubmit.submit.gobigger.level_2.submission_level_2_21",
            "GoBiggerSubmit.submit.gobigger.random.submission_random_46"
        ],
        "ranks": [
            0,
            3,
            2,
            1
        ],
        "scores": [
            34004.330147415596,
            30.781501543282243,
            72.50150866782485,
            12034.66874199465
        ],
        "time_actions": [
            9.54196047782898,
            0.015292644500732422,
            0.4816548824310303,
            0.05750250816345215
        ],
        "time_cost": 36.676358699798584
    },
    {
        "seed": 12038728,
        "submits": [
            "GoBiggerSubmit.submit.gobigger.level_1.submission_level_1_2",
            "GoBiggerSubmit.submit.gobigger.level_1.submission_level_1_49",
            "GoBiggerSubmit.submit.gobigger.level_2.submission_level_2_27",
            "GoBiggerSubmit.submit.gobigger.random.submission_random_23"
        ],
        "ranks": [
            1,
            0,
            2,
            3
        ],
        "scores": [
            32059.454707910238,
            40880.33327281241,
            3233.5216453339767,
            152.89382014518765
        ],
        "time_actions": [
            6.041613340377808,
            6.606505393981934,
            0.6634194850921631,
            0.032058000564575195
        ],
        "time_cost": 24.399760484695435
    },
    {
        "seed": 66662973,
        "submits": [
            "GoBiggerSubmit.submit.gobigger.level_1.submission_level_1_5",
            "GoBiggerSubmit.submit.jsonzb.test.test_1",
            "GoBiggerSubmit.submit.gobigger.level_3.submission_level_3_32",
            "GoBiggerSubmit.submit.gobigger.level_3.submission_level_3_0"
        ],
        "ranks": [
            2,
            1,
            0,
            3
        ],
        "scores": [
            18559.115146330994,
            23193.875328537564,
            34151.305517534696,
            15832.409331747154
        ],
        "time_actions": [
            5.169313430786133,
            4.095608711242676,
            2.6011300086975098,
            3.1515815258026123
        ],
        "time_cost": 22.939343690872192
    },
    {
        "seed": 86397832,
        "submits": [
            "GoBiggerSubmit.submit.gobigger.random.submission_random_2",
            "GoBiggerSubmit.submit.gobigger.level_2.submission_level_2_40",
            "GoBiggerSubmit.submit.gobigger.random.submission_random_24",
            "GoBiggerSubmit.submit.gobigger.random.submission_random_25"
        ],
        "ranks": [
            2,
            3,
            1,
            0
        ],
        "scores": [
            1438.3819666953991,
            163.44485493738856,
            1540.091313171067,
            2615.7070512884584
        ],
        "time_actions": [
            0.03770947456359863,
            0.4847071170806885,
            0.011638164520263672,
            0.025516271591186523
        ],
        "time_cost": 12.399272203445435
    }
]