[
    {
        "seed": 33741315,
        "submits": [
            "GoBiggerSubmit.submit.gobigger.random.submission_random_11",
            "GoBiggerSubmit.submit.cpp.2022_01_09.submission-5b0e3de2",
            "GoBiggerSubmit.submit.gobigger.level_3.submission_level_3_40",
            "GoBiggerSubmit.submit.gobigger.level_1.submission_level_1_3"
        ],
        "ranks": [
            3,
            0,
            2,
            1
        ],
        "scores": [
            102.09488753330557,
            76803.02564793885,
            7742.131877575559,
            12135.98983501139
        ],
        "time_actions": [
            0.04179239273071289,
            6.76188063621521,
            3.6215646266937256,
            5.015350818634033
        ],
        "time_cost": 24.582504272460938
    },
    {
        "seed": 22217397,
        "submits": [
            "GoBiggerSubmit.submit.gobigger.random.submission_random_15",
            "GoBiggerSubmit.submit.gobigger.level_1.submission_level_1_47",
            "GoBiggerSubmit.submit.gobigger.level_2.submission_level_2_35",
            "GoBiggerSubmit.submit.gobigger.random.submission_random_31"
        ],
        "ranks": [
            2,
            0,
            1,
            3
        ],
        "scores": [
            82.05158779765851,
            52118.09203883275,
            2502.888933222611,
            77.7069509925081
        ],
        "time_actions": [
            0.06487512588500977,
            12.540020227432251,
            0.6379745006561279,
            0.02491140365600586
        ],
        "time_cost": 28.755189180374146
    },
    {
        "seed": 37597951,
        "submits": [
            "GoBiggerSubmit.submit.gobigger.level_1.submission_level_1_3",
            "GoBiggerSubmit.submit.gobigger.level_3.submission_level_3_20",
            "GoBiggerSubmit.submit.gobigger.level_3.submission_level_3_43",
            "GoBiggerSubmit.submit.gobigger.level_1.submission_level_1_40"
        ],
        "ranks": [
            3,
            1,
            0,
            2
        ],
        "scores": [
            7034.968164385182,
            24129.69791790896,
            35463.36381888119,
            8681.143329015436
        ],
        "time_actions": [
            4.054049491882324,
            5.269923210144043,
            6.356496095657349,
            3.938102960586548
        ],
        "time_cost": 30.150270700454712
    },
    {
        "seed": 73052477,
        "submits": [
            "GoBiggerSubmit.submit.gobigger.random.submission_random_38",
            "GoBiggerSubmit.submit.gobigger.random.submission_random_30",
            "GoBiggerSubmit.submit.gobigger.level_1.submission_level_1_9",
            "GoBiggerSubmit.submit.gobigger.level_1.submission_level_1_40"
        ],
        "ranks": [
            2,
            3,
            1,
            0
        ],
        "scores": [
            3020.9561105717066,
            156.45700667605138,
            19087.832062808837,
            42291.16045517525
        ],
        "time_actions": [
            0.05300402641296387,
            0.01969623565673828,
            5.994207859039307,
            7.298538684844971
        ],
        "time_cost": 25.428807973861694
    },
    {
        "seed": 80211387,
        "submits": [
            "GoBiggerSubmit.submit.gobigger.level_2.submission_level_2_11",
            "GoBiggerSubmit.submit.gobigger.level_1.submission_level_1_22",
            "GoBiggerSubmit.submit.gobigger.level_1.submission_level_1_36",
            "GoBiggerSubmit.submit.gobigger.level_2.submission_level_2_25"
        ],
        "ranks": [
            1,
            0,
            2,
            3
        ],
        "scores": [
            11215.273889457538,
            61928.739036207495,
            4886.948288810885,
            62.872233110283446
        ],
        "time_actions": [
            0.6041672229766846,
            7.932063579559326,
            4.032211065292358,
            0.5662579536437988
        ],
        "time_cost": 22.11067819595337
    },
    {
        "seed": 92426597,
        "submits": [
            "GoBiggerSubmit.submit.gobigger.level_1.submission_level_1_0",
            "GoBiggerSubmit.submit.gobigger.level_2.submission_level_2_7",
            "GoBiggerSubmit.submit.gobigger.random.submission_random_8",
            "GoBiggerSubmit.submit.gobigger.level_2.submission_level_2_2"
        ],
        "ranks": [
            1,
            3,
            2,
            0
        ],
        "scores": [
            30151.115610522185,
            46.93956222539257,
            1169.2334692308239,
            31506.221645379832
        ],
        "time_actions": [
            10.788142204284668,
            0.4542868137359619,
            0.02899479866027832,
            1.2562618255615234
        ],
        "time_cost": 29.118916511535645
    },
    {
        "seed": 24178450,
        "submits": [
            "GoBiggerSubmit.submit.gobigger.level_2.submission_level_2_13",
            "GoBiggerSubmit.submit.gobigger.random.submission_random_16",
            "GoBiggerSubmit.submit.gobigger.level_2.submission_level_2_5",
            "GoBiggerSubmit.submit.gobigger.level_3.submission_level_3_36"
        ],
        "ranks": [
            2,
            3,
            1,
            0
        ],
        "scores": [
            1993.0477307148599,
            910.8618289909125,
            22378.69163561061,
            44572.99964634779
        ],
        "time_actions": [
            0.6437666416168213,
            0.08582806587219238,
            1.1782188415527344,
            8.512984037399292
        ],
        "time_cost": 28.81678557395935
    },
    {
        "seed": 30709699,
        "submits": [
            "GoBiggerSubmit.submit.gobigger.level_1.submission_level_1_2",
            "GoBiggerSubmit.submit.gobigger.level_1.submission_level_1_17",
            "GoBiggerSubmit.submit.gobigger.level_3.submission_level_3_4",
            "GoBiggerSubmit.submit.gobigger.level_3.submission_level_3_21"
        ],
        "ranks": [
            2,
            3,
            0,
            1
        ],
        "scores": [
            13567.039900756165,
            10452.290237201334,
            34144.483882685745,
            25499.905925028357
        ],
        "time_actions": [
            4.363265752792358,
            4.6296067237854,
            5.478192090988159,
            3.963541030883789
        ],
        "time_cost": 28.116719245910645
    },
    {
        "seed": 16001202,
        "submits": [
            "GoBiggerSubmit.submit.gobigger.level_2.submission_level_2_26",
            "GoBiggerSubmit.submit.gobigger.level_2.submission_level_2_13",
            "GoBiggerSubmit.submit.gobigger.level_2.submission_level_2_21",
            "GoBiggerSubmit.submit.gobigger.random.submission_random_11"
        ],
        "ranks": [
            2,
            3,
            0,
            1
        ],
        "scores": [
            158.47551261216947,
            98.7031027894084,
            8051.449003210354,
            1676.5532807676948
        ],
        "time_actions": [
            0.5653691291809082,
            0.46924352645874023,
            0.5124740600585938,
            0.03302478790283203
        ],
        "time_cost": 14.23046875
    },
    {
        "seed": 85472769,
        "submits": [
            "GoBiggerSubmit.submit.gobigger.level_3.submission_level_3_20",
            "GoBiggerSubmit.submit.gobigger.level_2.submission_level_2_49",
            "GoBiggerSubmit.submit.gobigger.level_2.submission_level_2_17",
            "GoBiggerSubmit.submit.gobigger.level_2.submission_level_2_47"
        ],
        "ranks": [
            0,
            3,
            1,
            2
        ],
        "scores": [
            41827.010982918575,
            27.0,
            11499.290127243296,
            62.89486557687338
        ],
        "time_actions": [
            10.504326581954956,
            0.5534839630126953,
            0.4981651306152344,
            0.5317161083221436
        ],
        "time_cost": 31.541776180267334
    },
    {
        "seed": 59604182,
        "submits": [
            "GoBiggerSubmit.submit.gobigger.random.submission_random_44",
            "GoBiggerSubmit.submit.gobigger.random.submission_random_41",
            "GoBiggerSubmit.submit.gobigger.random.submission_random_28",
            "GoBiggerSubmit.submit.cpp.21_12_24.submission-2b2ea0d7"
        ],
        "ranks": [
            3,
            1,
            2,
            0
        ],
        "scores": [
            277.8389988611181,
            2396.401500948673,
            864.5899467152492,
            33896.489277701025
        ],
        "time_actions": [
            0.0561671257019043,
            0.02045726776123047,
            0.020473718643188477,
            2.8623006343841553
        ],
        "time_cost": 24.42091131210327
    },
    {
        "seed": 50890434,
        "submits": [
            "GoBiggerSubmit.submit.gobigger.level_1.submission_level_1_1",
            "GoBiggerSubmit.submit.gobigger.level_2.submission_level_2_30",
            "GoBiggerSubmit.submit.gobigger.random.submission_random_0",
            "GoBiggerSubmit.submit.gobigger.level_2.submission_level_2_42"
        ],
        "ranks": [
            0,
            3,
            2,
            1
        ],
        "scores": [
            27565.053729817242,
            1655.4611675854364,
            8616.553023000755,
            9925.931221275483
        ],
        "time_actions": [
            7.545111894607544,
            0.5940046310424805,
            0.04533076286315918,
            0.5991003513336182
        ],
        "time_cost": 26.465603590011597
    },
    {
        "seed": 34737015,
        "submits": [
            "GoBiggerSubmit.submit.gobigger.level_3.submission_level_3_22",
            "GoBiggerSubmit.submit.gobigger.level_2.submission_level_2_10",
            "GoBiggerSubmit.submit.gobigger.random.submission_random_14",
            "GoBiggerSubmit.submit.gobigger.none.submission_none_1"
        ],
        "ranks": [
            0,
            1,
            2,
            3
        ],
        "scores": [
            41077.94873442079,
            5104.046596154092,
            3156.9688987739346,
            27.0
        ],
        "time_actions": [
            9.854841947555542,
            0.740635871887207,
            0.06945919990539551,
            0.0176544189453125
        ],
        "time_cost": 33.642868518829346
    },
    {
        "seed": 40923699,
        "submits": [
            "GoBiggerSubmit.submit.gobigger.level_1.submission_level_1_8",
            "GoBiggerSubmit.submit.gobigger.level_1.submission_level_1_28",
            "GoBiggerSubmit.submit.gobigger.level_1.submission_level_1_24",
            "GoBiggerSubmit.submit.gobigger.random.submission_random_26"
        ],
        "ranks": [
            0,
            1,
            3,
            2
        ],
        "scores": [
            33238.57619627067,
            22040.528742285638,
            4890.833743027286,
            5177.267927252686
        ],
        "time_actions": [
            6.742271661758423,
            5.430623769760132,
            3.8938252925872803,
            0.04931449890136719
        ],
        "time_cost": 26.22189497947693
    },
    {
        "seed": 89484782,
        "submits": [
            "GoBiggerSubmit.submit.gobigger.level_1.submission_level_1_35",
            "GoBiggerSubmit.submit.gobigger.level_3.submission_level_3_15",
            "GoBiggerSubmit.submit.gobigger.level_3.submission_level_3_23",
            "GoBiggerSubmit.submit.gobigger.level_2.submission_level_2_41"
        ],
        "ranks": [
            1,
            0,
            2,
            3
        ],
        "scores": [
            23760.391521064754,
            27278.306322663764,
            23681.210372139765,
            45.987898677583445
        ],
        "time_actions": [
            5.4393651485443115,
            5.1759185791015625,
            6.362043857574463,
            0.5701498985290527
        ],
        "time_cost": 30.436376571655273
    },
    {
        "seed": 73627182,
        "submits": [
            "GoBiggerSubmit.submit.gobigger.level_3.submission_level_3_17",
            "GoBiggerSubmit.submit.gobigger.level_2.submission_level_2_25",
            "GoBiggerSubmit.submit.gobigger.level_2.submission_level_2_22",
            "GoBiggerSubmit.submit.gobigger.level_3.submission_level_3_19"
        ],
        "ranks": [
            0,
            3,
            2,
            1
        ],
        "scores": [
            51234.84158361785,
            70.90164928264127,
            10277.413023669795,
            34377.151259825914
        ],
        "time_actions": [
            6.670475721359253,
            0.5458292961120605,
            0.6324481964111328,
            4.638142108917236
        ],
        "time_cost": 25.633659839630127
    },
    {
        "seed": 29830276,
        "submits": [
            "GoBiggerSubmit.submit.gobigger.level_3.submission_level_3_35",
            "GoBiggerSubmit.submit.gobigger.level_3.submission_level_3_16",
            "GoBiggerSubmit.submit.gobigger.level_2.submission_level_2_44",
            "GoBiggerSubmit.submit.gobigger.level_3.submission_level_3_27"
        ],
        "ranks": [
            0,
            2,
            3,
            1
        ],
        "scores": [
            37457.77608133644,
            22348.642445223275,
            34.5672932703027,
            23483.78042292474
        ],
        "time_actions": [
            5.122040271759033,
            5.386503219604492,
            0.6957247257232666,
            4.849354982376099
        ],
        "time_cost": 28.653053283691406
    },
    {
        "seed": 31484613,
        "submits": [
            "GoBiggerSubmit.submit.gobigger.random.submission_random_47",
            "GoBiggerSubmit.submit.gobigger.level_3.submission_level_3_28",
            "GoBiggerSubmit.submit.gobigger.level_3.submission_level_3_47",
            "GoBiggerSubmit.submit.gobigger.level_1.submission_level_1_19"
        ],
        "ranks": [
            3,
            2,
            0,
            1
        ],
        "scores": [
            9422.095519059847,
            9722.289432180758,
            29873.892960454687,
            19093.49610688524
        ],
        "time_actions": [
            0.04280972480773926,
            3.763162136077881,
            3.694162368774414,
            7.152851104736328
        ],
        "time_cost": 25.853583097457886
    },
    {
        "seed": 32703229,
        "submits": [
            "GoBiggerSubmit.submit.gobigger.level_3.submission_level_3_18",
            "GoBiggerSubmit.submit.gobigger.level_1.submission_level_1_43",
            "GoBiggerSubmit.submit.gobigger.level_1.submission_level_1_4",
            "GoBiggerSubmit.submit.gobigger.level_2.submission_level_2_25"
        ],
        "ranks": [
            0,
            2,
            1,
            3
        ],
        "scores": [
            40781.82171932106,
            7754.489285863397,
            18687.583987921476,
            42.62620285164233
        ],
        "time_actions": [
            4.497300624847412,
            3.2095706462860107,
            3.8171169757843018,
            0.4693024158477783
        ],
        "time_cost": 21.00656294822693
    },
    {
        "seed": 46644731,
        "submits": [
            "GoBiggerSubmit.submit.gobigger.random.submission_random_40",
            "GoBiggerSubmit.submit.gobigger.random.submission_random_49",
            "GoBiggerSubmit.submit.gobigger.random.submission_random_19",
            "GoBiggerSubmit.submit.gobigger.random.submission_random_43"
        ],
        "ranks": [
            2,
            3,
            1,
            0
        ],
        "scores": [
            2011.2944314592894,
            1587.7221727552603,
            2156.980570421889,
            2446.50979298722
        ],
        "time_actions": [
            0.040744781494140625,
            0.01866626739501953,
            0.009737491607666016,
            0.009159564971923828
        ],
        "time_cost": 13.632142782211304
    }
]