[
    {
        "seed": 72921659,
        "submits": [
            "GoBiggerSubmit.submit.gobigger.level_2.submission_level_2_2",
            "GoBiggerSubmit.submit.gobigger.level_3.submission_level_3_45",
            "GoBiggerSubmit.submit.gobigger.level_2.submission_level_2_1",
            "GoBiggerSubmit.submit.gobigger.level_2.submission_level_2_32"
        ],
        "ranks": [
            0,
            1,
            3,
            2
        ],
        "scores": [
            51206.29053490218,
            40353.19417800248,
            70.75465977936193,
            11927.252669540047
        ],
        "time_actions": [
            1.390730857849121,
            5.254202365875244,
            0.5952801704406738,
            0.8231489658355713
        ],
        "time_cost": 21.413650512695312
    },
    {
        "seed": 75530340,
        "submits": [
            "GoBiggerSubmit.submit.gobigger.level_2.submission_level_2_41",
            "GoBiggerSubmit.submit.gobigger.random.submission_random_3",
            "GoBiggerSubmit.submit.gobigger.level_3.submission_level_3_34",
            "GoBiggerSubmit.submit.gobigger.level_1.submission_level_1_8"
        ],
        "ranks": [
            3,
            2,
            0,
            1
        ],
        "scores": [
            63.22423748890123,
            634.8382765483025,
            45955.35439352681,
            27972.866765250288
        ],
        "time_actions": [
            0.8082695007324219,
            0.03186655044555664,
            7.217141151428223,
            9.31901478767395
        ],
        "time_cost": 30.370235204696655
    },
    {
        "seed": 96536563,
        "submits": [
            "GoBiggerSubmit.submit.gobigger.level_1.submission_level_1_25",
            "GoBiggerSubmit.submit.gobigger.level_2.submission_level_2_33",
            "GoBiggerSubmit.submit.gobigger.random.submission_random_10",
            "GoBiggerSubmit.submit.gobigger.level_1.submission_level_1_17"
        ],
        "ranks": [
            1,
            3,
            2,
            0
        ],
        "scores": [
            21506.97258377799,
            27.0,
            4005.5000045507786,
            45117.21197064464
        ],
        "time_actions": [
            7.344563245773315,
            0.6120514869689941,
            0.05450582504272461,
            7.638776779174805
        ],
        "time_cost": 29.488839626312256
    },
    {
        "seed": 49985793,
        "submits": [
            "GoBiggerSubmit.submit.gobigger.level_1.submission_level_1_1",
            "GoBiggerSubmit.submit.gobigger.level_2.submission_level_2_32",
            "GoBiggerSubmit.submit.gobigger.random.submission_random_38",
            "GoBiggerSubmit.submit.gobigger.level_1.submission_level_1_10"
        ],
        "ranks": [
            1,
            3,
            2,
            0
        ],
        "scores": [
            13589.159412698085,
            138.4134472217739,
            602.052502783271,
            42734.24723072738
        ],
        "time_actions": [
            6.815351247787476,
            0.6372418403625488,
            0.04309225082397461,
            8.128286123275757
        ],
        "time_cost": 29.11795949935913
    },
    {
        "seed": 78907574,
        "submits": [
            "GoBiggerSubmit.submit.gobigger.level_3.submission_level_3_32",
            "GoBiggerSubmit.submit.gobigger.level_3.submission_level_3_20",
            "GoBiggerSubmit.submit.gobigger.random.submission_random_9",
            "GoBiggerSubmit.submit.gobigger.level_1.submission_level_1_18"
        ],
        "ranks": [
            2,
            0,
            3,
            1
        ],
        "scores": [
            23188.746138827515,
            38077.56637038906,
            951.8583309024484,
            26968.56829991129
        ],
        "time_actions": [
            5.0064003467559814,
            8.53377914428711,
            0.04308772087097168,
            7.558231592178345
        ],
        "time_cost": 34.36835050582886
    },
    {
        "seed": 86959365,
        "submits": [
            "GoBiggerSubmit.submit.gobigger.random.submission_random_36",
            "GoBiggerSubmit.submit.gobigger.level_2.submission_level_2_22",
            "GoBiggerSubmit.submit.gobigger.level_3.submission_level_3_42",
            "GoBiggerSubmit.submit.gobigger.random.submission_random_0"
        ],
        "ranks": [
            2,
            3,
            0,
            1
        ],
        "scores": [
            373.014792755055,
            205.8237054460614,
            40640.73764951036,
            1765.0939273078366
        ],
        "time_actions": [
            0.07148098945617676,
            1.1056036949157715,
            11.677336931228638,
            0.04365396499633789
        ],
        "time_cost": 46.88928294181824
    },
    {
        "seed": 7022289,
        "submits": [
            "GoBiggerSubmit.submit.gobigger.level_2.submission_level_2_0",
            "GoBiggerSubmit.submit.gobigger.random.submission_random_23",
            "GoBiggerSubmit.submit.gobigger.random.submission_random_48",
            "GoBiggerSubmit.submit.gobigger.level_1.submission_level_1_15"
        ],
        "ranks": [
            3,
            1,
            2,
            0
        ],
        "scores": [
            197.01325580628654,
            12818.85870549603,
            311.9176722231069,
            34912.44861265256
        ],
        "time_actions": [
            1.2562952041625977,
            0.05305194854736328,
            0.028029918670654297,
            16.998557567596436
        ],
        "time_cost": 45.290966272354126
    },
    {
        "seed": 32881822,
        "submits": [
            "GoBiggerSubmit.submit.gobigger.random.submission_random_38",
            "GoBiggerSubmit.submit.gobigger.level_2.submission_level_2_16",
            "GoBiggerSubmit.submit.gobigger.random.submission_random_9",
            "GoBiggerSubmit.submit.gobigger.random.submission_random_15"
        ],
        "ranks": [
            1,
            3,
            2,
            0
        ],
        "scores": [
            1682.5469614198084,
            279.75332790624475,
            1027.3618470107224,
            2943.7851309476937
        ],
        "time_actions": [
            0.05865621566772461,
            0.9178352355957031,
            0.021570205688476562,
            0.011759519577026367
        ],
        "time_cost": 20.61738681793213
    },
    {
        "seed": 92883773,
        "submits": [
            "GoBiggerSubmit.submit.gobigger.level_2.submission_level_2_4",
            "GoBiggerSubmit.submit.gobigger.level_2.submission_level_2_0",
            "GoBiggerSubmit.submit.gobigger.random.submission_random_7",
            "GoBiggerSubmit.submit.gobigger.level_2.submission_level_2_36"
        ],
        "ranks": [
            1,
            3,
            2,
            0
        ],
        "scores": [
            35931.10248477597,
            1569.7391750496454,
            2309.036834791931,
            59237.80634028375
        ],
        "time_actions": [
            1.9174463748931885,
            0.5718491077423096,
            0.04459023475646973,
            1.3095366954803467
        ],
        "time_cost": 22.705405712127686
    },
    {
        "seed": 39606502,
        "submits": [
            "GoBiggerSubmit.submit.gobigger.random.submission_random_3",
            "GoBiggerSubmit.submit.gobigger.random.submission_random_34",
            "GoBiggerSubmit.submit.gobigger.level_2.submission_level_2_42",
            "GoBiggerSubmit.submit.gobigger.level_1.submission_level_1_37"
        ],
        "ranks": [
            0,
            2,
            3,
            1
        ],
        "scores": [
            13408.181015078577,
            10680.226951918426,
            271.82635314738866,
            11709.306207078374
        ],
        "time_actions": [
            0.08861684799194336,
            0.020253896713256836,
            0.7696642875671387,
            13.07845401763916
        ],
        "time_cost": 36.25805854797363
    },
    {
        "seed": 31210326,
        "submits": [
            "GoBiggerSubmit.submit.gobigger.level_3.submission_level_3_19",
            "GoBiggerSubmit.submit.gobigger.random.submission_random_28",
            "GoBiggerSubmit.submit.gobigger.level_1.submission_level_1_3",
            "GoBiggerSubmit.submit.gobigger.random.submission_random_29"
        ],
        "ranks": [
            0,
            3,
            1,
            2
        ],
        "scores": [
            42715.584249722204,
            2843.8314555771212,
            5879.498588302755,
            5529.3862124688685
        ],
        "time_actions": [
            8.35980749130249,
            0.04202675819396973,
            4.760050535202026,
            0.017117023468017578
        ],
        "time_cost": 30.541815996170044
    },
    {
        "seed": 94026813,
        "submits": [
            "GoBiggerSubmit.submit.gobigger.random.submission_random_4",
            "GoBiggerSubmit.submit.gobigger.random.submission_random_6",
            "GoBiggerSubmit.submit.gobigger.level_2.submission_level_2_17",
            "GoBiggerSubmit.submit.gobigger.level_1.submission_level_1_31"
        ],
        "ranks": [
            2,
            1,
            3,
            0
        ],
        "scores": [
            4009.9632865277035,
            9133.811828050768,
            321.2484796377369,
            33763.41552126097
        ],
        "time_actions": [
            0.04637765884399414,
            0.02024388313293457,
            0.7147703170776367,
            9.496624946594238
        ],
        "time_cost": 28.997128009796143
    },
    {
        "seed": 86126373,
        "submits": [
            "GoBiggerSubmit.submit.gobigger.level_3.submission_level_3_26",
            "GoBiggerSubmit.submit.gobigger.level_2.submission_level_2_28",
            "GoBiggerSubmit.submit.gobigger.level_3.submission_level_3_5",
            "GoBiggerSubmit.submit.gobigger.level_3.submission_level_3_17"
        ],
        "ranks": [
            0,
            3,
            1,
            2
        ],
        "scores": [
            29765.438864838525,
            10740.329813725426,
            24701.766604671895,
            21491.077715707215
        ],
        "time_actions": [
            6.976045846939087,
            0.7507703304290771,
            7.685136318206787,
            5.859931468963623
        ],
        "time_cost": 36.239967584609985
    },
    {
        "seed": 62088349,
        "submits": [
            "GoBiggerSubmit.submit.gobigger.level_3.submission_level_3_34",
            "GoBiggerSubmit.submit.gobigger.level_3.submission_level_3_39",
            "GoBiggerSubmit.submit.gobigger.level_2.submission_level_2_6",
            "GoBiggerSubmit.submit.gobigger.random.submission_random_48"
        ],
        "ranks": [
            0,
            1,
            3,
            2
        ],
        "scores": [
            36435.919795819456,
            29575.34303988004,
            204.8771087627503,
            2907.4593993761655
        ],
        "time_actions": [
            11.762675046920776,
            7.152444362640381,
            0.7200257778167725,
            0.03636980056762695
        ],
        "time_cost": 41.4952871799469
    },
    {
        "seed": 87667747,
        "submits": [
            "GoBiggerSubmit.submit.gobigger.level_3.submission_level_3_3",
            "GoBiggerSubmit.submit.gobigger.random.submission_random_26",
            "GoBiggerSubmit.submit.gobigger.random.submission_random_19",
            "GoBiggerSubmit.submit.gobigger.level_2.submission_level_2_8"
        ],
        "ranks": [
            0,
            1,
            2,
            3
        ],
        "scores": [
            41938.91332329018,
            5836.440030304779,
            3263.7014543673195,
            30.948750004118615
        ],
        "time_actions": [
            11.061452627182007,
            0.0296785831451416,
            0.027814865112304688,
            0.6989681720733643
        ],
        "time_cost": 38.829349756240845
    },
    {
        "seed": 79553748,
        "submits": [
            "GoBiggerSubmit.submit.gobigger.level_2.submission_level_2_28",
            "GoBiggerSubmit.submit.gobigger.level_2.submission_level_2_35",
            "GoBiggerSubmit.submit.gobigger.level_1.submission_level_1_32",
            "GoBiggerSubmit.submit.gobigger.level_1.submission_level_1_30"
        ],
        "ranks": [
            2,
            3,
            0,
            1
        ],
        "scores": [
            5743.336703046569,
            74.69559775638905,
            34622.053767887555,
            26702.54437567229
        ],
        "time_actions": [
            0.6240184307098389,
            0.6278386116027832,
            9.42302680015564,
            6.122534275054932
        ],
        "time_cost": 29.066227197647095
    },
    {
        "seed": 88423141,
        "submits": [
            "GoBiggerSubmit.submit.gobigger.level_2.submission_level_2_17",
            "GoBiggerSubmit.submit.gobigger.none.submission_none_0",
            "GoBiggerSubmit.submit.gobigger.level_1.submission_level_1_24",
            "GoBiggerSubmit.submit.gobigger.level_3.submission_level_3_41"
        ],
        "ranks": [
            2,
            3,
            1,
            0
        ],
        "scores": [
            1886.2803508889285,
            27.0,
            31012.762498448683,
            35758.72727423377
        ],
        "time_actions": [
            0.9240691661834717,
            0.01549530029296875,
            6.997883319854736,
            9.811461687088013
        ],
        "time_cost": 37.388829708099365
    },
    {
        "seed": 64342348,
        "submits": [
            "GoBiggerSubmit.submit.gobigger.level_3.submission_level_3_9",
            "GoBiggerSubmit.submit.gobigger.level_2.submission_level_2_1",
            "GoBiggerSubmit.submit.gobigger.random.submission_random_42",
            "GoBiggerSubmit.submit.gobigger.random.submission_random_38"
        ],
        "ranks": [
            0,
            3,
            2,
            1
        ],
        "scores": [
            35234.50737841496,
            133.57167976197982,
            804.7096951087967,
            4271.251007804544
        ],
        "time_actions": [
            7.375452041625977,
            0.7214727401733398,
            0.020147085189819336,
            0.019921541213989258
        ],
        "time_cost": 29.983781099319458
    },
    {
        "seed": 4422044,
        "submits": [
            "GoBiggerSubmit.submit.gobigger.level_2.submission_level_2_29",
            "GoBiggerSubmit.submit.gobigger.random.submission_random_37",
            "GoBiggerSubmit.submit.gobigger.level_3.submission_level_3_32",
            "GoBiggerSubmit.submit.gobigger.level_1.submission_level_1_21"
        ],
        "ranks": [
            2,
            3,
            0,
            1
        ],
        "scores": [
            4147.040863523145,
            1001.3698090862454,
            40001.03560295166,
            18282.847714663654
        ],
        "time_actions": [
            0.7494044303894043,
            0.04298710823059082,
            7.33598780632019,
            5.0397961139678955
        ],
        "time_cost": 29.887544870376587
    },
    {
        "seed": 20188586,
        "submits": [
            "GoBiggerSubmit.submit.gobigger.level_2.submission_level_2_14",
            "GoBiggerSubmit.submit.gobigger.level_1.submission_level_1_20",
            "GoBiggerSubmit.submit.gobigger.random.submission_random_48",
            "GoBiggerSubmit.submit.gobigger.level_3.submission_level_3_48"
        ],
        "ranks": [
            3,
            1,
            2,
            0
        ],
        "scores": [
            38.80653453679177,
            15092.108056677347,
            58.344491095442194,
            57051.248466149154
        ],
        "time_actions": [
            0.5405416488647461,
            6.864473342895508,
            0.029469013214111328,
            4.858615398406982
        ],
        "time_cost": 23.99088430404663
    }
]